{"frames": [

{
	"filename": "copybara_00000.png",
	"frame": {"x":0,"y":0,"w":250,"h":250},
	"rotated": false,
	"trimmed": false,
	"spriteSourceSize": {"x":0,"y":0,"w":250,"h":250},
	"sourceSize": {"w":250,"h":250}
},
{
	"filename": "copybara_00001.png",
	"frame": {"x":0,"y":250,"w":250,"h":250},
	"rotated": false,
	"trimmed": false,
	"spriteSourceSize": {"x":0,"y":0,"w":250,"h":250},
	"sourceSize": {"w":250,"h":250}
},
{
	"filename": "copybara_00002.png",
	"frame": {"x":0,"y":500,"w":250,"h":250},
	"rotated": false,
	"trimmed": false,
	"spriteSourceSize": {"x":0,"y":0,"w":250,"h":250},
	"sourceSize": {"w":250,"h":250}
},
{
	"filename": "copybara_00003.png",
	"frame": {"x":0,"y":750,"w":250,"h":250},
	"rotated": false,
	"trimmed": false,
	"spriteSourceSize": {"x":0,"y":0,"w":250,"h":250},
	"sourceSize": {"w":250,"h":250}
},
{
	"filename": "copybara_00004.png",
	"frame": {"x":0,"y":1000,"w":250,"h":250},
	"rotated": false,
	"trimmed": false,
	"spriteSourceSize": {"x":0,"y":0,"w":250,"h":250},
	"sourceSize": {"w":250,"h":250}
},
{
	"filename": "copybara_00005.png",
	"frame": {"x":0,"y":1250,"w":250,"h":250},
	"rotated": false,
	"trimmed": false,
	"spriteSourceSize": {"x":0,"y":0,"w":250,"h":250},
	"sourceSize": {"w":250,"h":250}
},
{
	"filename": "copybara_00006.png",
	"frame": {"x":0,"y":1500,"w":250,"h":250},
	"rotated": false,
	"trimmed": false,
	"spriteSourceSize": {"x":0,"y":0,"w":250,"h":250},
	"sourceSize": {"w":250,"h":250}
},
{
	"filename": "copybara_00007.png",
	"frame": {"x":0,"y":1750,"w":250,"h":250},
	"rotated": false,
	"trimmed": false,
	"spriteSourceSize": {"x":0,"y":0,"w":250,"h":250},
	"sourceSize": {"w":250,"h":250}
},
{
	"filename": "copybara_00008.png",
	"frame": {"x":250,"y":0,"w":250,"h":250},
	"rotated": false,
	"trimmed": false,
	"spriteSourceSize": {"x":0,"y":0,"w":250,"h":250},
	"sourceSize": {"w":250,"h":250}
},
{
	"filename": "copybara_00009.png",
	"frame": {"x":250,"y":250,"w":250,"h":250},
	"rotated": false,
	"trimmed": false,
	"spriteSourceSize": {"x":0,"y":0,"w":250,"h":250},
	"sourceSize": {"w":250,"h":250}
},
{
	"filename": "copybara_00010.png",
	"frame": {"x":250,"y":500,"w":250,"h":250},
	"rotated": false,
	"trimmed": false,
	"spriteSourceSize": {"x":0,"y":0,"w":250,"h":250},
	"sourceSize": {"w":250,"h":250}
},
{
	"filename": "copybara_00011.png",
	"frame": {"x":250,"y":750,"w":250,"h":250},
	"rotated": false,
	"trimmed": false,
	"spriteSourceSize": {"x":0,"y":0,"w":250,"h":250},
	"sourceSize": {"w":250,"h":250}
},
{
	"filename": "copybara_00012.png",
	"frame": {"x":250,"y":1000,"w":250,"h":250},
	"rotated": false,
	"trimmed": false,
	"spriteSourceSize": {"x":0,"y":0,"w":250,"h":250},
	"sourceSize": {"w":250,"h":250}
},
{
	"filename": "copybara_00013.png",
	"frame": {"x":250,"y":1250,"w":250,"h":250},
	"rotated": false,
	"trimmed": false,
	"spriteSourceSize": {"x":0,"y":0,"w":250,"h":250},
	"sourceSize": {"w":250,"h":250}
},
{
	"filename": "copybara_00014.png",
	"frame": {"x":250,"y":1500,"w":250,"h":250},
	"rotated": false,
	"trimmed": false,
	"spriteSourceSize": {"x":0,"y":0,"w":250,"h":250},
	"sourceSize": {"w":250,"h":250}
},
{
	"filename": "copybara_00015.png",
	"frame": {"x":250,"y":1750,"w":250,"h":250},
	"rotated": false,
	"trimmed": false,
	"spriteSourceSize": {"x":0,"y":0,"w":250,"h":250},
	"sourceSize": {"w":250,"h":250}
},
{
	"filename": "copybara_00016.png",
	"frame": {"x":500,"y":0,"w":250,"h":250},
	"rotated": false,
	"trimmed": false,
	"spriteSourceSize": {"x":0,"y":0,"w":250,"h":250},
	"sourceSize": {"w":250,"h":250}
},
{
	"filename": "copybara_00017.png",
	"frame": {"x":500,"y":250,"w":250,"h":250},
	"rotated": false,
	"trimmed": false,
	"spriteSourceSize": {"x":0,"y":0,"w":250,"h":250},
	"sourceSize": {"w":250,"h":250}
},
{
	"filename": "copybara_00018.png",
	"frame": {"x":500,"y":500,"w":250,"h":250},
	"rotated": false,
	"trimmed": false,
	"spriteSourceSize": {"x":0,"y":0,"w":250,"h":250},
	"sourceSize": {"w":250,"h":250}
},
{
	"filename": "copybara_00019.png",
	"frame": {"x":500,"y":750,"w":250,"h":250},
	"rotated": false,
	"trimmed": false,
	"spriteSourceSize": {"x":0,"y":0,"w":250,"h":250},
	"sourceSize": {"w":250,"h":250}
},
{
	"filename": "copybara_00020.png",
	"frame": {"x":500,"y":1000,"w":250,"h":250},
	"rotated": false,
	"trimmed": false,
	"spriteSourceSize": {"x":0,"y":0,"w":250,"h":250},
	"sourceSize": {"w":250,"h":250}
},
{
	"filename": "copybara_00021.png",
	"frame": {"x":500,"y":1250,"w":250,"h":250},
	"rotated": false,
	"trimmed": false,
	"spriteSourceSize": {"x":0,"y":0,"w":250,"h":250},
	"sourceSize": {"w":250,"h":250}
},
{
	"filename": "copybara_00022.png",
	"frame": {"x":500,"y":1500,"w":250,"h":250},
	"rotated": false,
	"trimmed": false,
	"spriteSourceSize": {"x":0,"y":0,"w":250,"h":250},
	"sourceSize": {"w":250,"h":250}
},
{
	"filename": "copybara_00023.png",
	"frame": {"x":500,"y":1750,"w":250,"h":250},
	"rotated": false,
	"trimmed": false,
	"spriteSourceSize": {"x":0,"y":0,"w":250,"h":250},
	"sourceSize": {"w":250,"h":250}
},
{
	"filename": "copybara_00024.png",
	"frame": {"x":750,"y":0,"w":250,"h":250},
	"rotated": false,
	"trimmed": false,
	"spriteSourceSize": {"x":0,"y":0,"w":250,"h":250},
	"sourceSize": {"w":250,"h":250}
},
{
	"filename": "copybara_00025.png",
	"frame": {"x":750,"y":250,"w":250,"h":250},
	"rotated": false,
	"trimmed": false,
	"spriteSourceSize": {"x":0,"y":0,"w":250,"h":250},
	"sourceSize": {"w":250,"h":250}
},
{
	"filename": "copybara_00026.png",
	"frame": {"x":750,"y":500,"w":250,"h":250},
	"rotated": false,
	"trimmed": false,
	"spriteSourceSize": {"x":0,"y":0,"w":250,"h":250},
	"sourceSize": {"w":250,"h":250}
},
{
	"filename": "copybara_00027.png",
	"frame": {"x":750,"y":750,"w":250,"h":250},
	"rotated": false,
	"trimmed": false,
	"spriteSourceSize": {"x":0,"y":0,"w":250,"h":250},
	"sourceSize": {"w":250,"h":250}
},
{
	"filename": "copybara_00028.png",
	"frame": {"x":750,"y":1000,"w":250,"h":250},
	"rotated": false,
	"trimmed": false,
	"spriteSourceSize": {"x":0,"y":0,"w":250,"h":250},
	"sourceSize": {"w":250,"h":250}
},
{
	"filename": "copybara_00029.png",
	"frame": {"x":750,"y":1250,"w":250,"h":250},
	"rotated": false,
	"trimmed": false,
	"spriteSourceSize": {"x":0,"y":0,"w":250,"h":250},
	"sourceSize": {"w":250,"h":250}
},
{
	"filename": "copybara_00030.png",
	"frame": {"x":750,"y":1500,"w":250,"h":250},
	"rotated": false,
	"trimmed": false,
	"spriteSourceSize": {"x":0,"y":0,"w":250,"h":250},
	"sourceSize": {"w":250,"h":250}
},
{
	"filename": "copybara_00031.png",
	"frame": {"x":750,"y":1750,"w":250,"h":250},
	"rotated": false,
	"trimmed": false,
	"spriteSourceSize": {"x":0,"y":0,"w":250,"h":250},
	"sourceSize": {"w":250,"h":250}
},
{
	"filename": "copybara_00032.png",
	"frame": {"x":1000,"y":0,"w":250,"h":250},
	"rotated": false,
	"trimmed": false,
	"spriteSourceSize": {"x":0,"y":0,"w":250,"h":250},
	"sourceSize": {"w":250,"h":250}
},
{
	"filename": "copybara_00033.png",
	"frame": {"x":1000,"y":250,"w":250,"h":250},
	"rotated": false,
	"trimmed": false,
	"spriteSourceSize": {"x":0,"y":0,"w":250,"h":250},
	"sourceSize": {"w":250,"h":250}
},
{
	"filename": "copybara_00034.png",
	"frame": {"x":1000,"y":500,"w":250,"h":250},
	"rotated": false,
	"trimmed": false,
	"spriteSourceSize": {"x":0,"y":0,"w":250,"h":250},
	"sourceSize": {"w":250,"h":250}
},
{
	"filename": "copybara_00035.png",
	"frame": {"x":1000,"y":750,"w":250,"h":250},
	"rotated": false,
	"trimmed": false,
	"spriteSourceSize": {"x":0,"y":0,"w":250,"h":250},
	"sourceSize": {"w":250,"h":250}
},
{
	"filename": "copybara_00036.png",
	"frame": {"x":1000,"y":1000,"w":250,"h":250},
	"rotated": false,
	"trimmed": false,
	"spriteSourceSize": {"x":0,"y":0,"w":250,"h":250},
	"sourceSize": {"w":250,"h":250}
},
{
	"filename": "copybara_00037.png",
	"frame": {"x":1000,"y":1250,"w":250,"h":250},
	"rotated": false,
	"trimmed": false,
	"spriteSourceSize": {"x":0,"y":0,"w":250,"h":250},
	"sourceSize": {"w":250,"h":250}
},
{
	"filename": "copybara_00038.png",
	"frame": {"x":1000,"y":1500,"w":250,"h":250},
	"rotated": false,
	"trimmed": false,
	"spriteSourceSize": {"x":0,"y":0,"w":250,"h":250},
	"sourceSize": {"w":250,"h":250}
},
{
	"filename": "copybara_00039.png",
	"frame": {"x":1000,"y":1750,"w":250,"h":250},
	"rotated": false,
	"trimmed": false,
	"spriteSourceSize": {"x":0,"y":0,"w":250,"h":250},
	"sourceSize": {"w":250,"h":250}
},
{
	"filename": "copybara_00040.png",
	"frame": {"x":1250,"y":0,"w":250,"h":250},
	"rotated": false,
	"trimmed": false,
	"spriteSourceSize": {"x":0,"y":0,"w":250,"h":250},
	"sourceSize": {"w":250,"h":250}
},
{
	"filename": "copybara_00041.png",
	"frame": {"x":1250,"y":250,"w":250,"h":250},
	"rotated": false,
	"trimmed": false,
	"spriteSourceSize": {"x":0,"y":0,"w":250,"h":250},
	"sourceSize": {"w":250,"h":250}
},
{
	"filename": "copybara_00042.png",
	"frame": {"x":1250,"y":500,"w":250,"h":250},
	"rotated": false,
	"trimmed": false,
	"spriteSourceSize": {"x":0,"y":0,"w":250,"h":250},
	"sourceSize": {"w":250,"h":250}
},
{
	"filename": "copybara_00043.png",
	"frame": {"x":1250,"y":750,"w":250,"h":250},
	"rotated": false,
	"trimmed": false,
	"spriteSourceSize": {"x":0,"y":0,"w":250,"h":250},
	"sourceSize": {"w":250,"h":250}
},
{
	"filename": "copybara_00044.png",
	"frame": {"x":1250,"y":1000,"w":250,"h":250},
	"rotated": false,
	"trimmed": false,
	"spriteSourceSize": {"x":0,"y":0,"w":250,"h":250},
	"sourceSize": {"w":250,"h":250}
},
{
	"filename": "copybara_00045.png",
	"frame": {"x":1250,"y":1250,"w":250,"h":250},
	"rotated": false,
	"trimmed": false,
	"spriteSourceSize": {"x":0,"y":0,"w":250,"h":250},
	"sourceSize": {"w":250,"h":250}
},
{
	"filename": "copybara_00046.png",
	"frame": {"x":1250,"y":1500,"w":250,"h":250},
	"rotated": false,
	"trimmed": false,
	"spriteSourceSize": {"x":0,"y":0,"w":250,"h":250},
	"sourceSize": {"w":250,"h":250}
}],
"meta": {
	"app": "https://www.codeandweb.com/texturepacker",
	"version": "1.0",
	"image": "capybara-0.png",
	"format": "RGBA8888",
	"size": {"w":1500,"h":2000},
	"scale": "1",
	"smartupdate": "$TexturePacker:SmartUpdate:602b97911ab9d27af65687d840ea8cd5:bb095d8b7fd5e96597d771f8994287a5:f194b11e744fb3594df042e90db55964$"
}
}
